igppack/__init__.py
igppack/commands/__init__.py
igppack/commands/eat.py
igppack/commands/giustizia.py
igppack/commands/rage.py
igppack/tables/__init__.py
igppack/tables/giustizia.py
igppack-1.0.0.dist-info/WHEEL
igppack-1.0.0.dist-info/METADATA
igppack-1.0.0.dist-info/RECORD
